Workbook

Sheet 取引台帳
A1: くまの酒店 取引台帳
A2: 対象期間：2026年1月〜2月
A4: No. | B4: 日付 | C4: 伝票番号 | D4: 区分 | E4: 取引先 | F4: 摘要 | G4: 税抜金額 | H4: 消費税 | I4: 税込金額 | J4: 入金 | K4: 出金
A5: 1 | B5: 46042 | C5: GS-2026-0412 | D5: 仕入 | E5: 月山酒造株式会社 | F5: 日本酒各種仕入代金（1月分） | G5: 150000 | H5: 15000 | I5: 165000 | K5: 165000
A6: 2 | B6: 46047 | C6: VT-26-0089 | D6: 仕入 | E6: 株式会社ヴィノテラス | F6: 輸入ワイン仕入代金 | G6: 210000 | H6: 21000 | I6: 231000 | K6: 231000
A7: 3 | B7: 46050 | C7: - | D7: 仕入 | E7: 薩摩酒造株式会社 | F7: 本格焼酎各種仕入代金（1月分） | G7: 100000 | H7: 10000 | I7: 110000 | K7: 110000
A8: 4 | B8: 46052 | C8: SJ-260130-012 | D8: 仕入 | E8: スピリッツジャパン株式会社 | F8: 輸入ウイスキー仕入代金 | G8: 180000 | H8: 18000 | I8: 198000 | K8: 198000
A9: 5 | B9: 46054 | C9: MZ-0261-0034 | D9: 仕入 | E9: 丸善食品株式会社 | F9: 食品・おつまみ仕入代金 | G9: 39800 | H9: 3980 | I9: 43780 | K9: 43780
A10: 6 | B10: 46054 | C10: HY-260201-078 | D10: 経費 | E10: はやて運送株式会社 | F10: 酒類配送運賃（1月分） | G10: 30000 | H10: 3000 | I10: 33000 | K10: 33000
A11: 7 | B11: 46054 | C11: SFR-2026-02 | D11: 経費 | E11: 世田谷不動産管理株式会社 | F11: 店舗賃料（2月分） | G11: 200000 | H11: 20000 | I11: 220000 | K11: 220000
A12: 8 | B12: 46056 | C12: - | D12: 仕入 | E12: 大和屋商店 | F12: ビール各種仕入代金（2月第1週分） | G12: 80000 | H12: 8000 | I12: 88000 | K12: 88000
A13: 9 | B13: 46056 | C13: SP-2026-0189 | D13: 経費 | E13: さくら印刷株式会社 | F13: 新春セールチラシ印刷代金（5000部） | G13: 40000 | H13: 4000 | I13: 44000 | K13: 44000
A14: 10 | B14: 46057 | C14: TB-2026-043 | D14: 仕入 | E14: TOKYOブルワリー株式会社 | F14: クラフトビール仕入代金 | G14: 72000 | H14: 7200 | I14: 79200 | K14: 79200
A15: 11 | B15: 46058 | C15: KS-2026-0198 | D15: 販売 | E15: 居酒屋 鶴亀 | F15: 酒類卸売代金（2月第1回納品分） | G15: 115000 | H15: 11500 | I15: 126500 | J15: 126500
A16: 12 | B16: 46058 | C16: TG-26020501 | D16: 仕入 | E16: 東洋ガラス販売株式会社 | F16: 酒器・グラス仕入代金 | G16: 32000 | H16: 3200 | I16: 35200 | K16: 35200
A17: 13 | B17: 46059 | C17: KS-2026-0205 | D17: 販売 | E17: 焼鳥 とりまさ | F17: 酒類卸売代金（2月第1回納品分） | G17: 62000 | H17: 6200 | I17: 68200 | J17: 68200
A18: 14 | B18: 46060 | C18: - | D18: 仕入 | E18: 越後鶴亀酒造株式会社 | F18: 新潟地酒各種仕入代金 | G18: 120000 | H18: 12000 | I18: 132000 | K18: 132000
A19: 15 | B19: 46061 | C19: No.4521 | D19: 販売 | E19: 個人客（店頭小売） | F19: 店頭販売（獺祭・プレモル他） | G19: 6500 | H19: 650 | I19: 7150 | J19: 7150
A20: 16 | B20: 46061 | C20: KS-2026-0210 | D20: 販売 | E20: グランドホテル経堂 | F20: 宴会用酒類納品代金 | G20: 230000 | H20: 23000 | I20: 253000 | J20: 253000
A21: 17 | B21: 46062 | C21: No.4587 | D21: 販売 | E21: 個人客（店頭小売） | F21: 店頭販売（久保田・黒霧島他） | G21: 11300 | H21: 1130 | I21: 12430 | J21: 12430
A22: 18 | B22: 46063 | C22: KS-2026-0201 | D22: 販売 | E22: マルト建設株式会社 | F22: 贈答用日本酒セット | G22: 50000 | H22: 5000 | I22: 55000 | J22: 55000
A23: 19 | B23: 46064 | C23: No.4602 | D23: 販売 | E23: 個人客（店頭小売） | F23: 店頭販売（十四代・響 ギフト用） | G23: 20800 | H23: 2080 | I23: 22880 | J23: 22880
A24: 20 | B24: 46065 | C24: KS-2026-0215 | D24: 販売 | E24: アニヴェルセル世田谷 | F24: 披露宴用酒類納品代金（2/15挙式分） | G24: 170000 | H24: 17000 | I24: 187000 | J24: 187000
A25: 合計 | G25: =SUM(G5:G24) -> 1919400 | H25: =SUM(H5:H24) -> 191940 | I25: =SUM(I5:I24) -> 2111340 | J25: =SUM(J5:J24) -> 732160 | K25: =SUM(K5:K24) -> 1379180

Sheet 区分別集計
A1: 区分別集計表
A3: 区分 | B3: 件数 | C3: 税抜合計 | D3: 消費税合計 | E3: 税込合計 | F3: 構成比
A4: 仕入 | B4: =COUNTIF(取引台帳!D5:D24,"仕入") -> 9 | C4: =SUMIF(取引台帳!D5:D24,"仕入",取引台帳!G5:G24) -> 983800 | D4: =SUMIF(取引台帳!D5:D24,"仕入",取引台帳!H5:H24) -> 98380 | E4: =SUMIF(取引台帳!D5:D24,"仕入",取引台帳!I5:I24) -> 1082180 | F4: =E4/E7 -> 0.51255601
A5: 販売 | B5: =COUNTIF(取引台帳!D5:D24,"販売") -> 8 | C5: =SUMIF(取引台帳!D5:D24,"販売",取引台帳!G5:G24) -> 665600 | D5: =SUMIF(取引台帳!D5:D24,"販売",取引台帳!H5:H24) -> 66560 | E5: =SUMIF(取引台帳!D5:D24,"販売",取引台帳!I5:I24) -> 732160 | F5: =E5/E7 -> 0.34677503
A6: 経費 | B6: =COUNTIF(取引台帳!D5:D24,"経費") -> 3 | C6: =SUMIF(取引台帳!D5:D24,"経費",取引台帳!G5:G24) -> 270000 | D6: =SUMIF(取引台帳!D5:D24,"経費",取引台帳!H5:H24) -> 27000 | E6: =SUMIF(取引台帳!D5:D24,"経費",取引台帳!I5:I24) -> 297000 | F6: =E6/E7 -> 0.14066896
A7: 合計 | B7: =SUM(B4:B6) -> 20 | C7: =SUM(C4:C6) -> 1919400 | D7: =SUM(D4:D6) -> 191940 | E7: =SUM(E4:E6) -> 2111340 | F7: 1
A9: 損益概要
A10: 売上高（税抜） | B10: =C5 -> 665600
A11: 仕入原価（税抜） | B11: =C4 -> 983800
A12: 売上総利益（粗利） | B12: =B10-B11 -> -318200
A13: 経費合計（税抜） | B13: =C6 -> 270000
A14: 営業利益 | B14: =B12-B13 -> -588200
A16: 粗利率 | B16: =IF(B10=0,0,B12/B10) -> -0.4780649
A17: 営業利益率 | B17: =IF(B10=0,0,B14/B10) -> -0.88371394

Sheet 取引先別集計
A1: 取引先別集計表
A3: 取引先 | B3: 区分 | C3: 取引回数 | D3: 税込合計 | E3: 備考
A4: 株式会社ヴィノテラス | B4: 仕入 | C4: 1 | D4: 231000 | E4: 輸入ワイン仕入代金
A5: スピリッツジャパン株式会社 | B5: 仕入 | C5: 1 | D5: 198000 | E5: 輸入ウイスキー仕入代金
A6: 月山酒造株式会社 | B6: 仕入 | C6: 1 | D6: 165000 | E6: 日本酒各種仕入代金（1月分）
A7: 越後鶴亀酒造株式会社 | B7: 仕入 | C7: 1 | D7: 132000 | E7: 新潟地酒各種仕入代金
A8: 薩摩酒造株式会社 | B8: 仕入 | C8: 1 | D8: 110000 | E8: 本格焼酎各種仕入代金（1月分）
A9: 大和屋商店 | B9: 仕入 | C9: 1 | D9: 88000 | E9: ビール各種仕入代金（2月第1週分）
A10: TOKYOブルワリー株式会社 | B10: 仕入 | C10: 1 | D10: 79200 | E10: クラフトビール仕入代金
A11: 丸善食品株式会社 | B11: 仕入 | C11: 1 | D11: 43780 | E11: 食品・おつまみ仕入代金
A12: 東洋ガラス販売株式会社 | B12: 仕入 | C12: 1 | D12: 35200 | E12: 酒器・グラス仕入代金
A13: グランドホテル経堂 | B13: 販売 | C13: 1 | D13: 253000 | E13: 宴会用酒類納品代金
A14: アニヴェルセル世田谷 | B14: 販売 | C14: 1 | D14: 187000 | E14: 披露宴用酒類納品代金（2/15挙式分）
A15: 居酒屋 鶴亀 | B15: 販売 | C15: 1 | D15: 126500 | E15: 酒類卸売代金（2月第1回納品分）
... A17: マルト建設株式会社 | B17: 販売 | C17: 1 | D17: 55000 | E17: 贈答用日本酒セット
A18: 個人客（店頭小売） | B18: 販売 | C18: 3 | D18: 42460
A19: 世田谷不動産管理株式会社 | B19: 経費 | C19: 1 | D19: 220000 | E19: 店舗賃料（2月分）
A20: さくら印刷株式会社 | B20: 経費 | C20: 1 | D20: 44000 | E20: 新春セールチラシ印刷代金（5000部）
A21: はやて運送株式会社 | B21: 経費 | C21: 1 | D21: 33000 | E21: 酒類配送運賃（1月分）
A22: 合計 | C22: =SUM(C4:C21) -> 20 | D22: =SUM(D4:D21) -> 2111340

Sheet 月別推移
A1: 月別推移表
A3: 月 | B3: 仕入（税込） | C3: 販売（税込） | D3: 経費（税込） | E3: 収支
A4: 2026年1月 | B4: =SUMPRODUCT((MONTH(取引台帳!B5:B24)=1)*(取引台帳!D5:D24="仕入")*取引台帳!I5:I24) -> 704000 | C4: =SUMPRODUCT((MONTH(取引台帳!B5:B24)=1)*(取引台帳!D5:D24="販売")*取引台帳!I5:I24) -> 0 | D4: =SUMPRODUCT((MONTH(取引台帳!B5:B24)=1)*(取引台帳!D5:D24="経費")*取引台帳!I5:I24) -> 0 | E4: =C4-B4-D4 -> -704000
A5: 2026年2月 | B5: =SUMPRODUCT((MONTH(取引台帳!B5:B24)=2)*(取引台帳!D5:D24="仕入")*取引台帳!I5:I24) -> 378180 | C5: =SUMPRODUCT((MONTH(取引台帳!B5:B24)=2)*(取引台帳!D5:D24="販売")*取引台帳!I5:I24) -> 732160 | D5: =SUMPRODUCT((MONTH(取引台帳!B5:B24)=2)*(取引台帳!D5:D24="経費")*取引台帳!I5:I24) -> 297000 | E5: =C5-B5-D5 -> 56980
A6: 合計 | B6: =SUM(B4:B5) -> 1082180 | C6: =SUM(C4:C5) -> 732160 | D6: =SUM(D4:D5) -> 297000 | E6: =SUM(E4:E5) -> -647020

Sheet 消費税集計
A1: 消費税集計表
A3: 項目 | B3: 税抜金額 | C3: 消費税額 | D3: 税込金額
A4: 売上に係る消費税（仮受消費税） | B4: =区分別集計!C5 -> 665600 | C4: =区分別集計!D5 -> 66560 | D4: =区分別集計!E5 -> 732160
A5: 仕入に係る消費税（仮払消費税） | B5: =区分別集計!C4 -> 983800 | C5: =区分別集計!D4 -> 98380 | D5: =区分別集計!E4 -> 1082180
A6: 経費に係る消費税（仮払消費税） | B6: =区分別集計!C6 -> 270000 | C6: =区分別集計!D6 -> 27000 | D6: =区分別集計!E6 -> 297000
A8: 消費税納付見込額 | C8: =C4-C5-C6 -> -58820
